imessage_wrapped/__init__.py
imessage_wrapped/imessage_wrapped.py
imessage_year_wrapped-1.0.0.dist-info/licenses/LICENSE
imessage_year_wrapped-1.0.0.dist-info/METADATA
imessage_year_wrapped-1.0.0.dist-info/WHEEL
imessage_year_wrapped-1.0.0.dist-info/entry_points.txt
imessage_year_wrapped-1.0.0.dist-info/top_level.txt
imessage_year_wrapped-1.0.0.dist-info/RECORD
